Metadata-Version: 1.1
Name: markovipy
Version: 0.1.1
Summary: Sentence generation using Markov Chains
Home-page: https://github.com/prodicus/markovipy
Author: Tasdik Rahman
Author-email: prodicus@outlook.com
License: GNU General Public License v3
Keywords: markovipy
Platform: UNKNOWN
Classifier: Development Status :: 2 - Pre-Alpha
Classifier: Intended Audience :: Developers
Classifier: License :: OSI Approved :: GNU General Public License v3 (GPLv3)
Classifier: Natural Language :: English
Classifier: Programming Language :: Python :: 2
Classifier: Programming Language :: Python :: 2.6
Classifier: Programming Language :: Python :: 2.7
Classifier: Programming Language :: Python :: 3
Classifier: Programming Language :: Python :: 3.3
Classifier: Programming Language :: Python :: 3.4
Classifier: Programming Language :: Python :: 3.5
